Metadata-Version: 2.1
Name: storage-sim
Version: 1.0.0b3
Summary: Discrete Event Simulator for Energy Storage Evaluation
Author: Will Vining, John Eddy, Ujjwol Tamrakar
Author-email: wfvinin@sandia.gov
License: BSD-3-Clause
Classifier: Programming Language :: Python :: 3
Classifier: Development Status :: 4 - Beta
License-File: LICENSE
Requires-Dist: helics[cli]
Requires-Dist: OpenDSSDirect.py[extras] >=0.5.0
Requires-Dist: networkx
Requires-Dist: importlib-resources
Requires-Dist: kivy
Requires-Dist: kivymd
Requires-Dist: tomli
Requires-Dist: requests
Requires-Dist: kivy-garden
Requires-Dist: scipy
Requires-Dist: matplotlib ~=3.7.2
